[
  {
    "_id": "66f6a5e4f08d9c050f9d7a1e",
    "cover": "66f66be63ccf61b8ed2f48e5",
    "signature": "67249b9b3d5dc5b7fa6e24a5",
    "tennant": "filipeni",
    "fullName": "Vasile Cara",
    "description": {
      "ro": "Vasile Cara este contabil-șef în cadrul Primăriei Filipeni, Leova, responsabil de gestionarea resurselor financiare ale instituției și de întocmirea rapoartelor contabile. El se ocupă de planificarea bugetului și monitorizarea cheltuielilor, asigurând transparența și eficiența financiară în primărie.",
      "ru": "Василе Кара – главный бухгалтер филипеньской мэрии Леова, отвечает за управление финансовыми ресурсами учреждения и подготовку бухгалтерских отчетов. Он отвечает за бюджетное планирование и мониторинг расходов, обеспечивая прозрачность и финансовую эффективность в мэрии.",
      "en": "Vasile Cara is the chief accountant in the Filipeni City Hall, Leova, responsible for managing the institution's financial resources and preparing accounting reports. He is in charge of budget planning and expenditure monitoring, ensuring transparency and financial efficiency in the town hall.",
      "uk": "",
      "bg": "",
      "tr": "",
      "gag": "",
      "fr": "",
      "de": "",
      "it": "",
      "es": "",
      "pt": "",
      "pl": "",
      "cs": "",
      "sk": "",
      "hu": "",
      "sr": "",
      "hr": "",
      "bs": "",
      "sl": "",
      "mk": "",
      "sq": "",
      "el": "",
      "nl": "",
      "da": "",
      "sv": "",
      "no": "",
      "fi": "",
      "et": "",
      "lv": "",
      "lt": "",
      "is": "",
      "mt": "",
      "ga": ""
    },
    "email": "vasilecara@mail.ru",
    "slug": "vasile-cara",
    "sections": [
      {
        "type": "CAPITALISED_PARAGRAPH",
        "content": {
          "ro": "Vasile Cara este contabil-șef al Primăriei Filipeni, absolvent al Academiei de Studii Economice din Chișinău (ASEM), cu o experiență vastă în gestionarea finanțelor publice. Cu o carieră de peste 34 de ani, el s-a remarcat prin cunoștințele și abilitățile profesionale excelente, având un rol esențial în administrarea corectă a fondurilor locale.\n\n",
          "ru": "Василе Кара – главный бухгалтер примэрии Филиппин, выпускник Кишинёвской экономической академии (ASEM) с большим опытом управления государственными финансами. За свою более чем 34-летнюю карьеру он отличился отличными профессиональными знаниями и навыками, сыграв ключевую роль в правильном управлении местными фондами.",
          "en": "Vasile Cara is the chief accountant of the Filipeni City Hall, a graduate of the Academy of Economic Studies in Chisinau (ASEM), with extensive experience in managing public finances. With a career spanning over 34 years, he has distinguished himself by his excellent professional knowledge and skills, playing a key role in the proper administration of local funds.",
          "uk": "",
          "bg": "",
          "tr": "",
          "gag": "",
          "fr": "",
          "de": "",
          "it": "",
          "es": "",
          "pt": "",
          "pl": "",
          "cs": "",
          "sk": "",
          "hu": "",
          "sr": "",
          "hr": "",
          "bs": "",
          "sl": "",
          "mk": "",
          "sq": "",
          "el": "",
          "nl": "",
          "da": "",
          "sv": "",
          "no": "",
          "fi": "",
          "et": "",
          "lv": "",
          "lt": "",
          "is": "",
          "mt": "",
          "ga": ""
        }
      },
      {
        "type": "PARAGRAPH",
        "content": {
          "ro": "Responsabilitatea de care dă dovadă în toate activitățile sale asigură o gestionare eficientă a bugetului și conformitatea cu reglementările legale. Vasile colaborează îndeaproape cu echipa primăriei, facilitând comunicarea și buna funcționare a activităților administrative. Spiritul său de echipă și atenția la detalii contribuie la îmbunătățirea continuă a proceselor financiare din cadrul administrației locale.\n\n",
          "ru": "Ответственность, которую он проявляет во всей своей деятельности, обеспечивает эффективное управление бюджетом и соблюдение правовых норм. Василе тесно сотрудничает с командой мэрии, способствуя общению и бесперебойному функционированию административной деятельности. Его командный дух и внимание к деталям способствуют постоянному совершенствованию финансовых процессов в местном самоуправлении.",
          "en": "The responsibility it shows in all its activities ensures efficient budget management and compliance with legal regulations. Vasile collaborates closely with the town hall team, facilitating communication and the smooth functioning of administrative activities. His team spirit and attention to detail contribute to the continuous improvement of financial processes within local government.",
          "uk": "",
          "bg": "",
          "tr": "",
          "gag": "",
          "fr": "",
          "de": "",
          "it": "",
          "es": "",
          "pt": "",
          "pl": "",
          "cs": "",
          "sk": "",
          "hu": "",
          "sr": "",
          "hr": "",
          "bs": "",
          "sl": "",
          "mk": "",
          "sq": "",
          "el": "",
          "nl": "",
          "da": "",
          "sv": "",
          "no": "",
          "fi": "",
          "et": "",
          "lv": "",
          "lt": "",
          "is": "",
          "mt": "",
          "ga": ""
        }
      }
    ],
    "experience": "34",
    "jobTitle": {
      "ro": "Contabil-șef\t",
      "ru": "Главный бухгалтер\t",
      "en": "Chief Accountant",
      "uk": "",
      "bg": "",
      "tr": "",
      "gag": "",
      "fr": "",
      "de": "",
      "it": "",
      "es": "",
      "pt": "",
      "pl": "",
      "cs": "",
      "sk": "",
      "hu": "",
      "sr": "",
      "hr": "",
      "bs": "",
      "sl": "",
      "mk": "",
      "sq": "",
      "el": "",
      "nl": "",
      "da": "",
      "sv": "",
      "no": "",
      "fi": "",
      "et": "",
      "lv": "",
      "lt": "",
      "is": "",
      "mt": "",
      "ga": ""
    },
    "skills": [
      {
        "title": {
          "ro": "Contabilitate",
          "ru": "Бухгалтерский учет",
          "en": "Accounting",
          "uk": "",
          "bg": "",
          "tr": "",
          "gag": "",
          "fr": "",
          "de": "",
          "it": "",
          "es": "",
          "pt": "",
          "pl": "",
          "cs": "",
          "sk": "",
          "hu": "",
          "sr": "",
          "hr": "",
          "bs": "",
          "sl": "",
          "mk": "",
          "sq": "",
          "el": "",
          "nl": "",
          "da": "",
          "sv": "",
          "no": "",
          "fi": "",
          "et": "",
          "lv": "",
          "lt": "",
          "is": "",
          "mt": "",
          "ga": ""
        },
        "value": 97
      },
      {
        "title": {
          "ro": "Responsabilitate",
          "ru": "Ответственность",
          "en": "Responsibility",
          "uk": "",
          "bg": "",
          "tr": "",
          "gag": "",
          "fr": "",
          "de": "",
          "it": "",
          "es": "",
          "pt": "",
          "pl": "",
          "cs": "",
          "sk": "",
          "hu": "",
          "sr": "",
          "hr": "",
          "bs": "",
          "sl": "",
          "mk": "",
          "sq": "",
          "el": "",
          "nl": "",
          "da": "",
          "sv": "",
          "no": "",
          "fi": "",
          "et": "",
          "lv": "",
          "lt": "",
          "is": "",
          "mt": "",
          "ga": ""
        },
        "value": 90
      },
      {
        "title": {
          "ro": "Colaborare ",
          "ru": "Сотрудничество",
          "en": "Collaboration",
          "uk": "",
          "bg": "",
          "tr": "",
          "gag": "",
          "fr": "",
          "de": "",
          "it": "",
          "es": "",
          "pt": "",
          "pl": "",
          "cs": "",
          "sk": "",
          "hu": "",
          "sr": "",
          "hr": "",
          "bs": "",
          "sl": "",
          "mk": "",
          "sq": "",
          "el": "",
          "nl": "",
          "da": "",
          "sv": "",
          "no": "",
          "fi": "",
          "et": "",
          "lv": "",
          "lt": "",
          "is": "",
          "mt": "",
          "ga": ""
        },
        "value": 85
      },
      {
        "title": {
          "ro": "Atenție la detalii",
          "ru": "Внимание к деталям",
          "en": "Attention to detail",
          "uk": "",
          "bg": "",
          "tr": "",
          "gag": "",
          "fr": "",
          "de": "",
          "it": "",
          "es": "",
          "pt": "",
          "pl": "",
          "cs": "",
          "sk": "",
          "hu": "",
          "sr": "",
          "hr": "",
          "bs": "",
          "sl": "",
          "mk": "",
          "sq": "",
          "el": "",
          "nl": "",
          "da": "",
          "sv": "",
          "no": "",
          "fi": "",
          "et": "",
          "lv": "",
          "lt": "",
          "is": "",
          "mt": "",
          "ga": ""
        },
        "value": 90
      }
    ],
    "phone": "68106447",
    "schools": [
      {
        "from": 1984,
        "to": 1989,
        "title": "ASEM Chișinău "
      }
    ],
    "order": 5
  },
  {
    "_id": "66f6ae9df08d9c050f9d7a26",
    "cover": "67220709870b84dbb34681d2",
    "signature": "67249b7f3d5dc5b7fa6e24a3",
    "tennant": "filipeni",
    "fullName": "Renata Camerzan",
    "description": {
      "ro": "Renata Camerzan este arhivist în cadrul Primăriei Filipeni, Leova, fiind responsabilă de organizarea și păstrarea documentelor oficiale ale primăriei. Ea gestionează arhivele istorice și curente, asigurând accesul și protecția acestora.",
      "ru": "Рената Камерзан — архивариус мэрии Филиппин, Леова, отвечает за организацию и хранение официальных документов мэрии. Он управляет историческими и текущими архивами, обеспечивая их доступ и защиту.",
      "en": "Renata Camerzan is an archivist at Filipeni City Hall, Leova, being responsible for organizing and keeping the city hall's official documents. It manages historical and current archives, ensuring their access and protection.",
      "uk": "",
      "bg": "",
      "tr": "",
      "gag": "",
      "fr": "",
      "de": "",
      "it": "",
      "es": "",
      "pt": "",
      "pl": "",
      "cs": "",
      "sk": "",
      "hu": "",
      "sr": "",
      "hr": "",
      "bs": "",
      "sl": "",
      "mk": "",
      "sq": "",
      "el": "",
      "nl": "",
      "da": "",
      "sv": "",
      "no": "",
      "fi": "",
      "et": "",
      "lv": "",
      "lt": "",
      "is": "",
      "mt": "",
      "ga": ""
    },
    "email": "Rena.camerzan@mail.ru ",
    "slug": "renata-camerzan",
    "sections": [
      {
        "type": "CAPITALISED_PARAGRAPH",
        "content": {
          "ro": "Renata Camerzan este arhivist în cadrul Primăriei Filipeni, absolventă a Universității Cooperatist Comerciale din Moldova, cu o experiență de 7 ani în domeniul arhivelor. Responsabilă și creativă, Renata se remarcă prin capacitatea sa de a organiza și gestiona documentele oficiale ale primăriei cu atenție și precizie.\n\n",
          "ru": "Рената Камерзан – архивариус примэрии Филиппин, выпускница Кооперативно-коммерческого университета Молдовы, с 7-летним опытом работы в сфере архивов. Ответственная и креативная, Рената выделяется своей способностью тщательно и точно организовывать и управлять официальными документами мэрии.",
          "en": "Renata Camerzan is an archivist at the Filipeni City Hall, a graduate of the Cooperative Commercial University of Moldova, with 7 years of experience in the field of archives. Responsible and creative, Renata stands out for her ability to organize and manage official city hall documents with care and precision.",
          "uk": "",
          "bg": "",
          "tr": "",
          "gag": "",
          "fr": "",
          "de": "",
          "it": "",
          "es": "",
          "pt": "",
          "pl": "",
          "cs": "",
          "sk": "",
          "hu": "",
          "sr": "",
          "hr": "",
          "bs": "",
          "sl": "",
          "mk": "",
          "sq": "",
          "el": "",
          "nl": "",
          "da": "",
          "sv": "",
          "no": "",
          "fi": "",
          "et": "",
          "lv": "",
          "lt": "",
          "is": "",
          "mt": "",
          "ga": ""
        }
      },
      {
        "type": "PARAGRAPH",
        "content": {
          "ro": "Colaborarea eficientă cu colegii și spiritul său de echipă contribuie la menținerea unei activități fluente în cadrul instituției. Cu abilități excelente de organizare și o atenție deosebită la detalii, Renata asigură păstrarea și gestionarea corectă a arhivelor, facilitând accesul rapid și eficient la documentele necesare.\n\n",
          "ru": "Эффективное сотрудничество с коллегами и командный дух способствуют поддержанию свободной деятельности внутри учреждения. Обладая отличными организаторскими способностями и большим вниманием к деталям, Рената обеспечивает надлежащую сохранность и управление архивами, обеспечивая быстрый и эффективный доступ к необходимым документам.",
          "en": "Effective collaboration with colleagues and his team spirit contribute to maintaining a fluent activity within the institution. With excellent organizational skills and great attention to detail, Renata ensures the proper preservation and management of archives, facilitating quick and efficient access to the necessary documents.",
          "uk": "",
          "bg": "",
          "tr": "",
          "gag": "",
          "fr": "",
          "de": "",
          "it": "",
          "es": "",
          "pt": "",
          "pl": "",
          "cs": "",
          "sk": "",
          "hu": "",
          "sr": "",
          "hr": "",
          "bs": "",
          "sl": "",
          "mk": "",
          "sq": "",
          "el": "",
          "nl": "",
          "da": "",
          "sv": "",
          "no": "",
          "fi": "",
          "et": "",
          "lv": "",
          "lt": "",
          "is": "",
          "mt": "",
          "ga": ""
        }
      },
      {
        "type": "GALLERY",
        "slidesPerView": 2,
        "content": [
          "67200b03ee25fe40ed70ff3c",
          "67200b04ee25fe40ed70ff47",
          "67200b03ee25fe40ed70ff3d"
        ]
      }
    ],
    "experience": "7",
    "jobTitle": {
      "ro": "Arhivist",
      "ru": "Архивист",
      "en": "Archivist",
      "uk": "",
      "bg": "",
      "tr": "",
      "gag": "",
      "fr": "",
      "de": "",
      "it": "",
      "es": "",
      "pt": "",
      "pl": "",
      "cs": "",
      "sk": "",
      "hu": "",
      "sr": "",
      "hr": "",
      "bs": "",
      "sl": "",
      "mk": "",
      "sq": "",
      "el": "",
      "nl": "",
      "da": "",
      "sv": "",
      "no": "",
      "fi": "",
      "et": "",
      "lv": "",
      "lt": "",
      "is": "",
      "mt": "",
      "ga": ""
    },
    "phone": "068569250",
    "skills": [
      {
        "title": {
          "ro": "Organizare și gestionare a arhivelor",
          "ru": "Организация и ведение архивов",
          "en": "Organization and management of archives",
          "uk": "",
          "bg": "",
          "tr": "",
          "gag": "",
          "fr": "",
          "de": "",
          "it": "",
          "es": "",
          "pt": "",
          "pl": "",
          "cs": "",
          "sk": "",
          "hu": "",
          "sr": "",
          "hr": "",
          "bs": "",
          "sl": "",
          "mk": "",
          "sq": "",
          "el": "",
          "nl": "",
          "da": "",
          "sv": "",
          "no": "",
          "fi": "",
          "et": "",
          "lv": "",
          "lt": "",
          "is": "",
          "mt": "",
          "ga": ""
        },
        "value": 100
      },
      {
        "title": {
          "ro": "Responsabilitate ",
          "ru": "Ответственность",
          "en": "Responsibility",
          "uk": "",
          "bg": "",
          "tr": "",
          "gag": "",
          "fr": "",
          "de": "",
          "it": "",
          "es": "",
          "pt": "",
          "pl": "",
          "cs": "",
          "sk": "",
          "hu": "",
          "sr": "",
          "hr": "",
          "bs": "",
          "sl": "",
          "mk": "",
          "sq": "",
          "el": "",
          "nl": "",
          "da": "",
          "sv": "",
          "no": "",
          "fi": "",
          "et": "",
          "lv": "",
          "lt": "",
          "is": "",
          "mt": "",
          "ga": ""
        },
        "value": 90
      },
      {
        "title": {
          "ro": "Creativitate",
          "ru": "Креативность",
          "en": "Creativity",
          "uk": "",
          "bg": "",
          "tr": "",
          "gag": "",
          "fr": "",
          "de": "",
          "it": "",
          "es": "",
          "pt": "",
          "pl": "",
          "cs": "",
          "sk": "",
          "hu": "",
          "sr": "",
          "hr": "",
          "bs": "",
          "sl": "",
          "mk": "",
          "sq": "",
          "el": "",
          "nl": "",
          "da": "",
          "sv": "",
          "no": "",
          "fi": "",
          "et": "",
          "lv": "",
          "lt": "",
          "is": "",
          "mt": "",
          "ga": ""
        },
        "value": 80
      },
      {
        "title": {
          "ro": "Lucru în echipă",
          "ru": "Работа в команде",
          "en": "Team work",
          "uk": "",
          "bg": "",
          "tr": "",
          "gag": "",
          "fr": "",
          "de": "",
          "it": "",
          "es": "",
          "pt": "",
          "pl": "",
          "cs": "",
          "sk": "",
          "hu": "",
          "sr": "",
          "hr": "",
          "bs": "",
          "sl": "",
          "mk": "",
          "sq": "",
          "el": "",
          "nl": "",
          "da": "",
          "sv": "",
          "no": "",
          "fi": "",
          "et": "",
          "lv": "",
          "lt": "",
          "is": "",
          "mt": "",
          "ga": ""
        },
        "value": 85
      },
      {
        "title": {
          "ro": "Atenție la detalii ",
          "ru": "Внимание к деталям",
          "en": "Attention to detail",
          "uk": "",
          "bg": "",
          "tr": "",
          "gag": "",
          "fr": "",
          "de": "",
          "it": "",
          "es": "",
          "pt": "",
          "pl": "",
          "cs": "",
          "sk": "",
          "hu": "",
          "sr": "",
          "hr": "",
          "bs": "",
          "sl": "",
          "mk": "",
          "sq": "",
          "el": "",
          "nl": "",
          "da": "",
          "sv": "",
          "no": "",
          "fi": "",
          "et": "",
          "lv": "",
          "lt": "",
          "is": "",
          "mt": "",
          "ga": ""
        },
        "value": 90
      }
    ],
    "schools": [
      {
        "from": 2003,
        "to": 2008,
        "title": "Universitatea Cooperatist Comercială din Moldova "
      }
    ],
    "order": 2
  },
  {
    "_id": "66f6ade2f08d9c050f9d7a24",
    "cover": "6722076a870b84dbb34681d3",
    "signature": "67249b9b3d5dc5b7fa6e24a5",
    "tennant": "filipeni",
    "fullName": "Lidia Cara",
    "description": {
      "ro": "Lidia Cara este specialist în percepere fiscală în cadrul Primăriei Filipeni, Leova, având responsabilitatea de a colecta și gestiona impozitele și taxele locale. Ea asigură conformitatea fiscală și contribuie la bunul mers al finanțelor publice locale.\n\n\n\n\n\n\n",
      "ru": "Лидия Кара — специалист по сбору налогов в мэрии Филиппин, Леова. Она отвечает за сбор и управление местными налогами и сборами. Это обеспечивает соблюдение налогово-бюджетной политики и способствует бесперебойной работе местных государственных финансов.",
      "en": "Lidia Cara is a tax collection specialist at Filipeni City Hall, Leova, having the responsibility of collecting and managing local taxes and fees. It ensures fiscal compliance and contributes to the smooth running of local public finances.",
      "uk": "",
      "bg": "",
      "tr": "",
      "gag": "",
      "fr": "",
      "de": "",
      "it": "",
      "es": "",
      "pt": "",
      "pl": "",
      "cs": "",
      "sk": "",
      "hu": "",
      "sr": "",
      "hr": "",
      "bs": "",
      "sl": "",
      "mk": "",
      "sq": "",
      "el": "",
      "nl": "",
      "da": "",
      "sv": "",
      "no": "",
      "fi": "",
      "et": "",
      "lv": "",
      "lt": "",
      "is": "",
      "mt": "",
      "ga": ""
    },
    "email": "lidiacara@mail.ru",
    "slug": "lidia-cara",
    "sections": [
      {
        "type": "CAPITALISED_PARAGRAPH",
        "content": {
          "ro": "Lidia Cara este perceptor fiscal în cadrul Primăriei Filipeni, absolventă a Academiei de Studii Economice din Moldova (ASEM), cu o experiență de peste 11 ani în administrarea fiscală. Cunoscătoare desăvârșită a domeniului, Lidia gestionează cu precizie colectarea impozitelor și taxelor locale, asumându-și responsabilitatea pentru corectitudinea și calitatea activităților sale.\n\n",
          "ru": "Лидия Кара — сборщик налогов примэрии Филиппин, выпускница Академии экономических исследований Молдовы (ASEM), с более чем 11-летним опытом работы в сфере налогового администрирования. Будучи абсолютным экспертом в этой области, Лидия четко управляет сбором местных налогов и сборов, беря на себя ответственность за правильность и качество своей деятельности.",
          "en": "Lidia Cara is a tax collector at the Filipeni City Hall, a graduate of the Academy of Economic Studies from Moldova (ASEM), with over 11 years of experience in tax administration. A complete expert in the field, Lidia manages the collection of local taxes and fees with precision, taking responsibility for the correctness and quality of her activities.",
          "uk": "",
          "bg": "",
          "tr": "",
          "gag": "",
          "fr": "",
          "de": "",
          "it": "",
          "es": "",
          "pt": "",
          "pl": "",
          "cs": "",
          "sk": "",
          "hu": "",
          "sr": "",
          "hr": "",
          "bs": "",
          "sl": "",
          "mk": "",
          "sq": "",
          "el": "",
          "nl": "",
          "da": "",
          "sv": "",
          "no": "",
          "fi": "",
          "et": "",
          "lv": "",
          "lt": "",
          "is": "",
          "mt": "",
          "ga": ""
        }
      },
      {
        "type": "PARAGRAPH",
        "content": {
          "ro": "Comunicarea eficientă și spiritul de echipă o recomandă ca un profesionist de încredere, capabilă să colaboreze excelent cu colegii și cetățenii. Lidia este apreciată pentru creativitatea sa în soluționarea provocărilor fiscale și pentru angajamentul de a respecta cele mai înalte standarde profesionale în activitatea de zi cu zi.\n\nComunicarea eficientă și spiritul de echipă o recomandă ca un profesionist de încredere, capabilă să colaboreze excelent cu colegii și cetățenii. Lidia este apreciată pentru creativitatea sa în soluționarea provocărilor fiscale și pentru angajamentul de a respecta cele mai înalte standarde profesionale în activitatea de zi cu zi.\n\n",
          "ru": "Эффективное общение и командный дух рекомендуют ее как надежного профессионала, умеющего прекрасно сотрудничать с коллегами и гражданами. Лидию ценят за ее творческий подход к решению финансовых проблем и за ее приверженность самым высоким профессиональным стандартам в своей повседневной работе.",
          "en": "Effective communication and team spirit recommend her as a reliable professional, able to collaborate excellently with colleagues and citizens. Lidia is appreciated for her creativity in solving fiscal challenges and for her commitment to the highest professional standards in her day-to-day work.",
          "uk": "",
          "bg": "",
          "tr": "",
          "gag": "",
          "fr": "",
          "de": "",
          "it": "",
          "es": "",
          "pt": "",
          "pl": "",
          "cs": "",
          "sk": "",
          "hu": "",
          "sr": "",
          "hr": "",
          "bs": "",
          "sl": "",
          "mk": "",
          "sq": "",
          "el": "",
          "nl": "",
          "da": "",
          "sv": "",
          "no": "",
          "fi": "",
          "et": "",
          "lv": "",
          "lt": "",
          "is": "",
          "mt": "",
          "ga": ""
        }
      },
      {
        "type": "GALLERY",
        "slidesPerView": 2,
        "content": [
          "67200b03ee25fe40ed70ff2b",
          "67200b04ee25fe40ed70ff42",
          "67200b04ee25fe40ed70ff43"
        ]
      }
    ],
    "experience": "11",
    "jobTitle": {
      "ro": "Specialist în percepere fiscală\t",
      "ru": "Специалист по сбору налогов",
      "en": "Tax collection specialist",
      "uk": "",
      "bg": "",
      "tr": "",
      "gag": "",
      "fr": "",
      "de": "",
      "it": "",
      "es": "",
      "pt": "",
      "pl": "",
      "cs": "",
      "sk": "",
      "hu": "",
      "sr": "",
      "hr": "",
      "bs": "",
      "sl": "",
      "mk": "",
      "sq": "",
      "el": "",
      "nl": "",
      "da": "",
      "sv": "",
      "no": "",
      "fi": "",
      "et": "",
      "lv": "",
      "lt": "",
      "is": "",
      "mt": "",
      "ga": ""
    },
    "phone": "068463672",
    "skills": [
      {
        "title": {
          "ro": "Cunoștințe și abilități profesionale în fiscalitate ",
          "ru": "Профессиональные знания и навыки в области налогообложения",
          "en": "Professional knowledge and skills in taxation",
          "uk": "",
          "bg": "",
          "tr": "",
          "gag": "",
          "fr": "",
          "de": "",
          "it": "",
          "es": "",
          "pt": "",
          "pl": "",
          "cs": "",
          "sk": "",
          "hu": "",
          "sr": "",
          "hr": "",
          "bs": "",
          "sl": "",
          "mk": "",
          "sq": "",
          "el": "",
          "nl": "",
          "da": "",
          "sv": "",
          "no": "",
          "fi": "",
          "et": "",
          "lv": "",
          "lt": "",
          "is": "",
          "mt": "",
          "ga": ""
        },
        "value": 95
      },
      {
        "title": {
          "ro": "Responsabilitate ",
          "ru": "Ответственность",
          "en": "Responsibility",
          "uk": "",
          "bg": "",
          "tr": "",
          "gag": "",
          "fr": "",
          "de": "",
          "it": "",
          "es": "",
          "pt": "",
          "pl": "",
          "cs": "",
          "sk": "",
          "hu": "",
          "sr": "",
          "hr": "",
          "bs": "",
          "sl": "",
          "mk": "",
          "sq": "",
          "el": "",
          "nl": "",
          "da": "",
          "sv": "",
          "no": "",
          "fi": "",
          "et": "",
          "lv": "",
          "lt": "",
          "is": "",
          "mt": "",
          "ga": ""
        },
        "value": 85
      },
      {
        "title": {
          "ro": "Comunicare eficientă ",
          "ru": "Эффективное общение",
          "en": "Effective communication",
          "uk": "",
          "bg": "",
          "tr": "",
          "gag": "",
          "fr": "",
          "de": "",
          "it": "",
          "es": "",
          "pt": "",
          "pl": "",
          "cs": "",
          "sk": "",
          "hu": "",
          "sr": "",
          "hr": "",
          "bs": "",
          "sl": "",
          "mk": "",
          "sq": "",
          "el": "",
          "nl": "",
          "da": "",
          "sv": "",
          "no": "",
          "fi": "",
          "et": "",
          "lv": "",
          "lt": "",
          "is": "",
          "mt": "",
          "ga": ""
        },
        "value": 85
      },
      {
        "title": {
          "ro": "Spirit de lucru în echipă ",
          "ru": "Командный дух работы",
          "en": "Team work spirit",
          "uk": "",
          "bg": "",
          "tr": "",
          "gag": "",
          "fr": "",
          "de": "",
          "it": "",
          "es": "",
          "pt": "",
          "pl": "",
          "cs": "",
          "sk": "",
          "hu": "",
          "sr": "",
          "hr": "",
          "bs": "",
          "sl": "",
          "mk": "",
          "sq": "",
          "el": "",
          "nl": "",
          "da": "",
          "sv": "",
          "no": "",
          "fi": "",
          "et": "",
          "lv": "",
          "lt": "",
          "is": "",
          "mt": "",
          "ga": ""
        },
        "value": 90
      },
      {
        "title": {
          "ro": "Creativitate ",
          "ru": "Креативность",
          "en": "Creativity",
          "uk": "",
          "bg": "",
          "tr": "",
          "gag": "",
          "fr": "",
          "de": "",
          "it": "",
          "es": "",
          "pt": "",
          "pl": "",
          "cs": "",
          "sk": "",
          "hu": "",
          "sr": "",
          "hr": "",
          "bs": "",
          "sl": "",
          "mk": "",
          "sq": "",
          "el": "",
          "nl": "",
          "da": "",
          "sv": "",
          "no": "",
          "fi": "",
          "et": "",
          "lv": "",
          "lt": "",
          "is": "",
          "mt": "",
          "ga": ""
        },
        "value": 85
      }
    ],
    "schools": [
      {
        "from": 1983,
        "to": 1988,
        "title": "ASEM Chișinău "
      }
    ],
    "order": 4
  },
  {
    "_id": "66f66bcd3ccf61b8ed2f48e3",
    "cover": "672202b2870b84dbb34681cf",
    "signature": "67249b7f3d5dc5b7fa6e24a3",
    "tennant": "filipeni",
    "fullName": "Tudor Camerzan\t",
    "description": {
      "ro": "Tudor Camerzan, primarul satului Filipeni din raionul Leova, este un lider local dedicat comunității sale. Având o viziune orientată spre dezvoltarea satului, el se concentrează pe îmbunătățirea infrastructurii și a serviciilor locale, precum și pe atragerea de fonduri pentru proiecte comunitare. Tudor Camerzan este cunoscut pentru abordarea sa proactivă și deschiderea către nevoile cetățenilor, punând accent pe colaborarea cu locuitorii pentru a găsi soluții eficiente pentru problemele satului.\n\n\n\n\n\n\n",
      "ru": "Тудор Камерзан, мэр села Филипень в районе Леова, является местным лидером, преданным своей общине. Имея видение, ориентированное на развитие деревень, он фокусируется на улучшении местной инфраструктуры и услуг, а также сборе средств для общественных проектов. Тудор Камерзан известен своим активным подходом и открытостью к потребностям горожан, уделяя особое внимание сотрудничеству с жителями для поиска эффективных решений проблем села.",
      "en": "Tudor Camerzan, the mayor of Filipeni village in Leova district, is a local leader dedicated to his community. With a village development-oriented vision, he focuses on improving local infrastructure and services, as well as raising funds for community projects. Tudor Camerzan is known for his proactive approach and openness to the needs of the citizens, emphasizing collaboration with the residents to find effective solutions for the village's problems."
    },
    "email": "tudor.camerzan@gmail.com",
    "slug": "tudor-camerzan",
    "sections": [
      {
        "type": "TITLE",
        "content": {
          "ro": "Tudor Camerzan – Primar al satului Filipeni, Raionul Leova",
          "ru": "Тудор Камерзан – примар села Филипень Леовского района",
          "en": "Tudor Camerzan – Mayor of Filipeni village, Leova District"
        }
      },
      {
        "type": "PARAGRAPH",
        "content": {
          "ro": "Tudor Camerzan este primarul satului Filipeni, un lider tânăr, energic și dedicat comunității pe care o reprezintă. După o luptă electorală strânsă în 2020, în care a obținut funcția de primar, el s-a impus ca un lider care pune accent pe dezvoltarea satului și pe îmbunătățirea condițiilor de trai pentru cetățeni. Absolvent al Universității de Studii Politice și Economice Europene „Constantin Stere” din Chișinău, cu o licență în științe politice, specializat în Relații Internaționale, Tudor și-a continuat formarea profesională printr-un masterat la Universitatea „Alexandru Ioan Cuza” din Iași.\n\n",
          "ru": "Тудор Камерзан — мэр села Филипень, молодой, энергичный и преданный своему делу лидер общества, которое он представляет. После упорной избирательной борьбы в 2020 году, в которой он получил должность мэра, он зарекомендовал себя как лидер, делающий упор на развитие села и улучшение условий жизни горожан. Выпускник Университета европейских политических и экономических исследований «Константин Стере» в Кишиневе по специальности «политология» по специальности «Международные отношения», Тудор продолжил свою профессиональную подготовку, получив степень магистра в Университете «Александру Иоан Куза» в Яссах.",
          "en": "Tudor Camerzan is the mayor of the village of Filipeni, a young, energetic and dedicated leader to the community he represents. After a close electoral battle in 2020, in which he obtained the position of mayor, he established himself as a leader who emphasizes the development of the village and the improvement of living conditions for citizens. A graduate of the \"Constantin Stere\" University of European Political and Economic Studies in Chisinau, with a degree in political science, specializing in International Relations, Tudor continued his professional training with a master's degree at the \"Alexandru Ioan Cuza\" University in Iași."
        }
      },
      {
        "type": "LIST",
        "content": [
          {
            "ro": "Ca primar, Tudor Camerzan se remarcă printr-o abordare proactivă și eficientă. Reușește să planifice și să administreze resursele și activitatea echipei în mod optim, anticipând provocările și găsind soluții eficiente. Deciziile sale au avut un impact pozitiv asupra activității instituției, optimizând procesele și îmbunătățind funcționarea administrației locale.",
            "ru": "На посту мэра Тудор Камерзан выделяется своим активным и эффективным подходом. Способен оптимально планировать и управлять ресурсами, а также работать в команде, предвидя проблемы и находя эффективные решения. Его решения положительно повлияли на деятельность учреждения, оптимизируя процессы и улучшая работу местной администрации.",
            "en": "As mayor, Tudor Camerzan stands out for his proactive and efficient approach. Able to plan and manage resources and team work optimally, anticipating challenges and finding effective solutions. His decisions had a positive impact on the institution's activity, optimizing processes and improving the functioning of local administration."
          }
        ]
      },
      {
        "type": "PARAGRAPH",
        "content": {
          "ro": "Tudor este cunoscut pentru colaborarea strânsă cu cetățenii, ascultându-le nevoile și prioritățile. El își canalizează eforturile spre dezvoltarea infrastructurii locale și atragerea de fonduri pentru proiectele comunitare, contribuind activ la modernizarea satului Filipeni. Cu o viziune clară și orientată spre dezvoltare, Tudor Camerzan continuă să fie un lider care își asumă deciziile și răspunderea pentru îmbunătățirea constantă a vieții comunității.\n\n",
          "ru": "Тудор известен тем, что тесно сотрудничает с гражданами, прислушиваясь к их потребностям и приоритетам. Он направляет свои усилия на развитие местной инфраструктуры и привлечение средств для общественных проектов, активно способствуя модернизации села Филипень. Имея четкое и ориентированное на развитие видение, Тудор Камерзан продолжает оставаться лидером, который принимает решения и несет ответственность за постоянное улучшение общественной жизни.",
          "en": "Tudor is known for working closely with citizens, listening to their needs and priorities. He channels his efforts towards the development of local infrastructure and attracting funds for community projects, actively contributing to the modernization of Filipeni village. With a clear and development-oriented vision, Tudor Camerzan continues to be a leader who takes decisions and responsibility for the constant improvement of community life."
        }
      },
      {
        "type": "GALLERY",
        "slidesPerView": 2,
        "content": [
          "67200b0cee25fe40ed70ffd1",
          "6705a9718221e9146ea19c41",
          "6705a9758221e9146ea19c42",
          "67200b0cee25fe40ed70ffd6"
        ]
      }
    ],
    "experience": "5",
    "jobTitle": {
      "ro": "Primar",
      "ru": "Мэр",
      "en": "Mayor"
    },
    "skills": [
      {
        "title": {
          "ro": "Planificare strategică ",
          "ru": "Стратегическое планирование",
          "en": "Strategic planning"
        },
        "value": 95
      },
      {
        "title": {
          "ro": "Luarea deciziilor",
          "ru": "Принятие решений",
          "en": "Decision making"
        },
        "value": 90
      },
      {
        "title": {
          "ro": "Gestionarea echipei",
          "ru": "Управление командой",
          "en": "Team management"
        },
        "value": 95
      },
      {
        "title": {
          "ro": "Leadership și responsabilitate",
          "ru": "Лидерство и подотчетность",
          "en": "Leadership and accountability"
        },
        "value": 100
      },
      {
        "title": {
          "ro": "Soluționarea problemelor",
          "ru": "Решение проблем",
          "en": "Solving problems"
        },
        "value": 90
      },
      {
        "title": {
          "ro": "Motivare pentru echipă",
          "ru": "Мотивация для команды",
          "en": "Motivation for the team"
        },
        "value": 95
      }
    ],
    "phone": "26340698",
    "socialLinks": [
      {
        "type": "facebook",
        "link": "https://www.facebook.com/tudor.camerzan"
      }
    ],
    "schools": [
      {
        "from": 2015,
        "to": 2018,
        "title": "Universitatea de Studii Politice și Economice Europene ”Constantin Stere”"
      },
      {
        "from": 2018,
        "to": 2020,
        "title": "Masterat Universitatea”Alexandru Ioan Cuza” din Iași"
      }
    ]
  },
  {
    "_id": "66f6abf8f08d9c050f9d7a20",
    "cover": "672206a4870b84dbb34681d1",
    "signature": "67249bac3d5dc5b7fa6e24a6",
    "tennant": "filipeni",
    "fullName": "Svetlana Boiștean\t",
    "description": {
      "ro": "Svetlana Boiștean este specialist în relații funciare și cadastru în cadrul Primăriei Filipeni, Leova, fiind responsabilă de gestionarea documentației cadastrale și a relațiilor funciare. Ea se ocupă de înregistrarea proprietăților, actualizarea planurilor cadastrale și asigurarea conformității legale în tranzacțiile funciare.",
      "ru": "Светлана Боистян является специалистом по земельным отношениям и кадастру в мэрии Филиппин города Леова и отвечает за управление кадастровой документацией и земельными отношениями. Он занимается регистрацией собственности, обновлением кадастровых планов и обеспечением соблюдения законодательства при сделках с землей.",
      "en": "Svetlana Boistean is a specialist in land relations and cadastre within Filipeni City Hall, Leova, being responsible for managing cadastral documentation and land relations. It deals with property registration, updating cadastral plans and ensuring legal compliance in land transactions.",
      "uk": "",
      "bg": "",
      "tr": "",
      "gag": "",
      "fr": "",
      "de": "",
      "it": "",
      "es": "",
      "pt": "",
      "pl": "",
      "cs": "",
      "sk": "",
      "hu": "",
      "sr": "",
      "hr": "",
      "bs": "",
      "sl": "",
      "mk": "",
      "sq": "",
      "el": "",
      "nl": "",
      "da": "",
      "sv": "",
      "no": "",
      "fi": "",
      "et": "",
      "lv": "",
      "lt": "",
      "is": "",
      "mt": "",
      "ga": ""
    },
    "email": "Sboisteanu.a@mail.com ",
    "slug": "svetlana-boistean",
    "sections": [
      {
        "type": "CAPITALISED_PARAGRAPH",
        "content": {
          "ro": "Svetlana Boișteanu este inginer cadastru și specialist în relații funciare în cadrul Primăriei Filipeni, absolventă a Universității Agrare de Stat din Moldova. Cu o experiență de peste 11 ani în acest domeniu, Svetlana se remarcă prin cunoștințele sale profesionale deosebite și capacitatea de a administra eficient problemele cadastrale și funciare ale comunității.",
          "ru": "Светлана Бойштяну – кадастровый инженер и специалист по земельным отношениям примэрии Филиппин, выпускница Государственного аграрного университета Молдовы. Обладая более чем 11-летним опытом работы в этой области, Светлана выделяется своими исключительными профессиональными знаниями и способностью эффективно решать кадастровые и земельные вопросы сообщества.",
          "en": "Svetlana Boișteanu is a cadastral engineer and specialist in land relations within the Filipeni City Hall, a graduate of the State Agrarian University of Moldova. With over 11 years of experience in this field, Svetlana stands out for her exceptional professional knowledge and ability to efficiently administer the cadastral and land issues of the community.",
          "uk": "",
          "bg": "",
          "tr": "",
          "gag": "",
          "fr": "",
          "de": "",
          "it": "",
          "es": "",
          "pt": "",
          "pl": "",
          "cs": "",
          "sk": "",
          "hu": "",
          "sr": "",
          "hr": "",
          "bs": "",
          "sl": "",
          "mk": "",
          "sq": "",
          "el": "",
          "nl": "",
          "da": "",
          "sv": "",
          "no": "",
          "fi": "",
          "et": "",
          "lv": "",
          "lt": "",
          "is": "",
          "mt": "",
          "ga": ""
        }
      },
      {
        "type": "PARAGRAPH",
        "content": {
          "ro": "Responsabilitatea și atenția la detalii o fac o profesionistă de încredere, iar comunicarea eficientă și spiritul de lucru în echipă contribuie la colaborarea armonioasă cu colegii și cetățenii. Svetlana este apreciată pentru abilitatea sa de a rezolva conflictele funciare și de a asigura conformitatea cu reglementările legale, având un rol esențial în gestionarea corectă a proprietăților din Filipeni.\n\n",
          "ru": "Ответственность и внимание к деталям делают ее надежным профессионалом, а эффективное общение и командная работа способствуют гармоничному сотрудничеству с коллегами и гражданами. Светлану ценят за ее способность разрешать земельные споры и обеспечивать соблюдение правовых норм, играя ключевую роль в правильном управлении недвижимостью на Филиппинах.",
          "en": "Responsibility and attention to detail make her a reliable professional, and effective communication and teamwork contribute to harmonious collaboration with colleagues and citizens. Svetlana is valued for her ability to resolve land disputes and ensure compliance with legal regulations, playing a key role in the proper management of properties in the Philippines.",
          "uk": "",
          "bg": "",
          "tr": "",
          "gag": "",
          "fr": "",
          "de": "",
          "it": "",
          "es": "",
          "pt": "",
          "pl": "",
          "cs": "",
          "sk": "",
          "hu": "",
          "sr": "",
          "hr": "",
          "bs": "",
          "sl": "",
          "mk": "",
          "sq": "",
          "el": "",
          "nl": "",
          "da": "",
          "sv": "",
          "no": "",
          "fi": "",
          "et": "",
          "lv": "",
          "lt": "",
          "is": "",
          "mt": "",
          "ga": ""
        }
      },
      {
        "type": "GALLERY",
        "content": [
          "67200b03ee25fe40ed70ff3b"
        ]
      }
    ],
    "experience": "11",
    "jobTitle": {
      "ro": "Specialist în relații funciare și cadastru\t",
      "ru": "Специалист по земельным отношениям и кадастру",
      "en": "Specialist in land relations and cadastre",
      "uk": "",
      "bg": "",
      "tr": "",
      "gag": "",
      "fr": "",
      "de": "",
      "it": "",
      "es": "",
      "pt": "",
      "pl": "",
      "cs": "",
      "sk": "",
      "hu": "",
      "sr": "",
      "hr": "",
      "bs": "",
      "sl": "",
      "mk": "",
      "sq": "",
      "el": "",
      "nl": "",
      "da": "",
      "sv": "",
      "no": "",
      "fi": "",
      "et": "",
      "lv": "",
      "lt": "",
      "is": "",
      "mt": "",
      "ga": ""
    },
    "phone": "067479389",
    "skills": [
      {
        "title": {
          "ro": "Cunoștințe și abilități profesionale în cadastru ",
          "ru": "Профессиональные знания и навыки в области кадастра",
          "en": "Professional knowledge and skills in cadastre",
          "uk": "",
          "bg": "",
          "tr": "",
          "gag": "",
          "fr": "",
          "de": "",
          "it": "",
          "es": "",
          "pt": "",
          "pl": "",
          "cs": "",
          "sk": "",
          "hu": "",
          "sr": "",
          "hr": "",
          "bs": "",
          "sl": "",
          "mk": "",
          "sq": "",
          "el": "",
          "nl": "",
          "da": "",
          "sv": "",
          "no": "",
          "fi": "",
          "et": "",
          "lv": "",
          "lt": "",
          "is": "",
          "mt": "",
          "ga": ""
        },
        "value": 95
      },
      {
        "title": {
          "ro": "Spirit de lucru în echipă",
          "ru": "Командный дух работы",
          "en": "Team work spirit",
          "uk": "",
          "bg": "",
          "tr": "",
          "gag": "",
          "fr": "",
          "de": "",
          "it": "",
          "es": "",
          "pt": "",
          "pl": "",
          "cs": "",
          "sk": "",
          "hu": "",
          "sr": "",
          "hr": "",
          "bs": "",
          "sl": "",
          "mk": "",
          "sq": "",
          "el": "",
          "nl": "",
          "da": "",
          "sv": "",
          "no": "",
          "fi": "",
          "et": "",
          "lv": "",
          "lt": "",
          "is": "",
          "mt": "",
          "ga": ""
        },
        "value": 90
      },
      {
        "title": {
          "ro": "Rezolvarea conflictelor",
          "ru": "Разрешение конфликтов",
          "en": "Conflict resolution",
          "uk": "",
          "bg": "",
          "tr": "",
          "gag": "",
          "fr": "",
          "de": "",
          "it": "",
          "es": "",
          "pt": "",
          "pl": "",
          "cs": "",
          "sk": "",
          "hu": "",
          "sr": "",
          "hr": "",
          "bs": "",
          "sl": "",
          "mk": "",
          "sq": "",
          "el": "",
          "nl": "",
          "da": "",
          "sv": "",
          "no": "",
          "fi": "",
          "et": "",
          "lv": "",
          "lt": "",
          "is": "",
          "mt": "",
          "ga": ""
        },
        "value": 85
      },
      {
        "title": {
          "ro": "Responsabilitate ",
          "ru": "Ответственность",
          "en": "Responsibility",
          "uk": "",
          "bg": "",
          "tr": "",
          "gag": "",
          "fr": "",
          "de": "",
          "it": "",
          "es": "",
          "pt": "",
          "pl": "",
          "cs": "",
          "sk": "",
          "hu": "",
          "sr": "",
          "hr": "",
          "bs": "",
          "sl": "",
          "mk": "",
          "sq": "",
          "el": "",
          "nl": "",
          "da": "",
          "sv": "",
          "no": "",
          "fi": "",
          "et": "",
          "lv": "",
          "lt": "",
          "is": "",
          "mt": "",
          "ga": ""
        },
        "value": 90
      }
    ],
    "schools": [
      {
        "from": 1987,
        "to": 1991,
        "title": "Centrul de Excelenţă în Economie şi Finanţe"
      },
      {
        "from": 2015,
        "to": 2019,
        "title": "Universitatea Agrară de Stat din Moldova "
      }
    ],
    "order": 3
  },
  {
    "_id": "66f6a340f08d9c050f9d7a1c",
    "cover": "6722064c870b84dbb34681d0",
    "signature": "67249b8d3d5dc5b7fa6e24a4",
    "tennant": "filipeni",
    "fullName": "Ecaterina Vîlcu\t",
    "description": {
      "ro": "Ecaterina Vîlcu este secretară în cadrul Primăriei Filipeni, Leova. Ea joacă un rol esențial în buna funcționare administrativă a instituției, gestionând corespondența, programările și comunicarea între primar și cetățeni.\n\n\n\n\n\n\n",
      "ru": "Екатерина Вылку — секретарь филиппинской мэрии Леова. Она играет важную роль в хорошем административном функционировании учреждения, управляя перепиской, назначениями и общением между мэром и гражданами.",
      "en": "Ecaterina Vîlcu is a secretary at the Filipeni City Hall, Leova. She plays an essential role in the good administrative functioning of the institution, managing correspondence, appointments and communication between the mayor and citizens.",
      "uk": "",
      "bg": "",
      "tr": "",
      "gag": "",
      "fr": "",
      "de": "",
      "it": "",
      "es": "",
      "pt": "",
      "pl": "",
      "cs": "",
      "sk": "",
      "hu": "",
      "sr": "",
      "hr": "",
      "bs": "",
      "sl": "",
      "mk": "",
      "sq": "",
      "el": "",
      "nl": "",
      "da": "",
      "sv": "",
      "no": "",
      "fi": "",
      "et": "",
      "lv": "",
      "lt": "",
      "is": "",
      "mt": "",
      "ga": ""
    },
    "email": "vilcuecaterina1978@gmail.com ",
    "slug": "ecaterina-vilcu",
    "sections": [
      {
        "type": "CAPITALISED_PARAGRAPH",
        "content": {
          "ro": "Ecaterina Vîlcu este secretara Consiliului Local din Filipeni, o persoană dedicată și responsabilă care aduce un plus de valoare administrației locale prin abilitățile sale excelente de comunicare și colaborare. Absolventă a Universității Pedagogice de Stat „Ion Creangă” din Chișinău, Ecaterina și-a construit cariera în cadrul administrației publice, contribuind semnificativ la îmbunătățirea imaginii autorităților locale.",
          "ru": "Екатерина Вылку — секретарь местного совета Филиппин, преданный своему делу и ответственный человек, который приносит дополнительную пользу местной администрации благодаря своим отличным навыкам общения и сотрудничества. Выпускница Кишиневского государственного педагогического университета «Ион Крянгэ», Екатерина построила свою карьеру в сфере государственного управления, внося значительный вклад в улучшение имиджа местных властей.",
          "en": "Ecaterina Vîlcu is the secretary of the Filipeni Local Council, a dedicated and responsible person who brings added value to the local administration through her excellent communication and collaboration skills. A graduate of the \"Ion Creangă\" State Pedagogical University in Chisinau, Ecaterina built her career in public administration, significantly contributing to improving the image of local authorities.",
          "uk": "",
          "bg": "",
          "tr": "",
          "gag": "",
          "fr": "",
          "de": "",
          "it": "",
          "es": "",
          "pt": "",
          "pl": "",
          "cs": "",
          "sk": "",
          "hu": "",
          "sr": "",
          "hr": "",
          "bs": "",
          "sl": "",
          "mk": "",
          "sq": "",
          "el": "",
          "nl": "",
          "da": "",
          "sv": "",
          "no": "",
          "fi": "",
          "et": "",
          "lv": "",
          "lt": "",
          "is": "",
          "mt": "",
          "ga": ""
        }
      },
      {
        "type": "PARAGRAPH",
        "content": {
          "ro": "Cu un spirit de echipă deosebit, Ecaterina facilitează colaborarea eficientă între consilieri și cetățeni, având un impact pozitiv asupra realizării obiectivelor comunitare. Comunicarea sa de înaltă calitate cu locuitorii a fost un factor esențial în îmbunătățirea relațiilor dintre cetățeni și autorități. Creativitatea și responsabilitatea de care dă dovadă în activitatea sa zilnică o definesc ca un membru esențial al administrației locale.\n\n",
          "ru": "Обладая особым командным духом, Екатерина способствует эффективному сотрудничеству между советниками и гражданами, оказывая положительное влияние на достижение целей сообщества. Его качественное общение с жителями стало ключевым фактором улучшения отношений между гражданами и властью. Креативность и ответственность, которые она проявляет в своей повседневной работе, определяют ее как важного члена местной администрации.",
          "en": "With a special team spirit, Ecaterina facilitates effective collaboration between councilors and citizens, having a positive impact on the achievement of community objectives. His high-quality communication with residents was a key factor in improving relations between citizens and authorities. The creativity and responsibility she shows in her daily work define her as an essential member of the local administration.",
          "uk": "",
          "bg": "",
          "tr": "",
          "gag": "",
          "fr": "",
          "de": "",
          "it": "",
          "es": "",
          "pt": "",
          "pl": "",
          "cs": "",
          "sk": "",
          "hu": "",
          "sr": "",
          "hr": "",
          "bs": "",
          "sl": "",
          "mk": "",
          "sq": "",
          "el": "",
          "nl": "",
          "da": "",
          "sv": "",
          "no": "",
          "fi": "",
          "et": "",
          "lv": "",
          "lt": "",
          "is": "",
          "mt": "",
          "ga": ""
        }
      },
      {
        "type": "GALLERY",
        "slidesPerView": 2,
        "content": [
          "67200b04ee25fe40ed70ff47",
          "67200b03ee25fe40ed70ff37"
        ]
      }
    ],
    "experience": "13",
    "jobTitle": {
      "ro": "Secretar",
      "ru": "Секретарь",
      "en": "Secretary",
      "uk": "",
      "bg": "",
      "tr": "",
      "gag": "",
      "fr": "",
      "de": "",
      "it": "",
      "es": "",
      "pt": "",
      "pl": "",
      "cs": "",
      "sk": "",
      "hu": "",
      "sr": "",
      "hr": "",
      "bs": "",
      "sl": "",
      "mk": "",
      "sq": "",
      "el": "",
      "nl": "",
      "da": "",
      "sv": "",
      "no": "",
      "fi": "",
      "et": "",
      "lv": "",
      "lt": "",
      "is": "",
      "mt": "",
      "ga": ""
    },
    "skills": [
      {
        "title": {
          "ro": "Comunicare eficientă ",
          "ru": "Эффективное общение",
          "en": "Effective communication",
          "uk": "",
          "bg": "",
          "tr": "",
          "gag": "",
          "fr": "",
          "de": "",
          "it": "",
          "es": "",
          "pt": "",
          "pl": "",
          "cs": "",
          "sk": "",
          "hu": "",
          "sr": "",
          "hr": "",
          "bs": "",
          "sl": "",
          "mk": "",
          "sq": "",
          "el": "",
          "nl": "",
          "da": "",
          "sv": "",
          "no": "",
          "fi": "",
          "et": "",
          "lv": "",
          "lt": "",
          "is": "",
          "mt": "",
          "ga": ""
        },
        "value": 95
      },
      {
        "title": {
          "ro": "Responsabilitate ",
          "ru": "Ответственность",
          "en": "Responsibility",
          "uk": "",
          "bg": "",
          "tr": "",
          "gag": "",
          "fr": "",
          "de": "",
          "it": "",
          "es": "",
          "pt": "",
          "pl": "",
          "cs": "",
          "sk": "",
          "hu": "",
          "sr": "",
          "hr": "",
          "bs": "",
          "sl": "",
          "mk": "",
          "sq": "",
          "el": "",
          "nl": "",
          "da": "",
          "sv": "",
          "no": "",
          "fi": "",
          "et": "",
          "lv": "",
          "lt": "",
          "is": "",
          "mt": "",
          "ga": ""
        },
        "value": 90
      },
      {
        "title": {
          "ro": "Spirit de echipă",
          "ru": "Командный дух",
          "en": "Team spirit",
          "uk": "",
          "bg": "",
          "tr": "",
          "gag": "",
          "fr": "",
          "de": "",
          "it": "",
          "es": "",
          "pt": "",
          "pl": "",
          "cs": "",
          "sk": "",
          "hu": "",
          "sr": "",
          "hr": "",
          "bs": "",
          "sl": "",
          "mk": "",
          "sq": "",
          "el": "",
          "nl": "",
          "da": "",
          "sv": "",
          "no": "",
          "fi": "",
          "et": "",
          "lv": "",
          "lt": "",
          "is": "",
          "mt": "",
          "ga": ""
        },
        "value": 95
      },
      {
        "title": {
          "ro": "Creativitate",
          "ru": "Креативность",
          "en": "Creativity",
          "uk": "",
          "bg": "",
          "tr": "",
          "gag": "",
          "fr": "",
          "de": "",
          "it": "",
          "es": "",
          "pt": "",
          "pl": "",
          "cs": "",
          "sk": "",
          "hu": "",
          "sr": "",
          "hr": "",
          "bs": "",
          "sl": "",
          "mk": "",
          "sq": "",
          "el": "",
          "nl": "",
          "da": "",
          "sv": "",
          "no": "",
          "fi": "",
          "et": "",
          "lv": "",
          "lt": "",
          "is": "",
          "mt": "",
          "ga": ""
        },
        "value": 85
      },
      {
        "title": {
          "ro": "Colaborare interinstituțională",
          "ru": "Межинституциональное сотрудничество",
          "en": "Inter-institutional collaboration",
          "uk": "",
          "bg": "",
          "tr": "",
          "gag": "",
          "fr": "",
          "de": "",
          "it": "",
          "es": "",
          "pt": "",
          "pl": "",
          "cs": "",
          "sk": "",
          "hu": "",
          "sr": "",
          "hr": "",
          "bs": "",
          "sl": "",
          "mk": "",
          "sq": "",
          "el": "",
          "nl": "",
          "da": "",
          "sv": "",
          "no": "",
          "fi": "",
          "et": "",
          "lv": "",
          "lt": "",
          "is": "",
          "mt": "",
          "ga": ""
        },
        "value": 90
      }
    ],
    "phone": "69741844",
    "schools": [
      {
        "from": 2002,
        "to": 2005,
        "title": "Universitatea Pedagogică de Stat ”Ion Creangă” din Chișinău"
      }
    ],
    "order": 1
  },
  {
    "_id": "66f6b11df08d9c050f9d7a2a",
    "cover": "672207ce870b84dbb34681d4",
    "signature": "67249bcd3d5dc5b7fa6e24a7",
    "tennant": "filipeni",
    "fullName": "Rodica Munteanu",
    "description": {
      "ro": "Rodica Munteanu este bibliotecară în cadrul Primăriei Filipeni, Leova. Ea se ocupă de administrarea colecțiilor de cărți și resurse de lectură, facilitând accesul comunității la informație și cultură. Rodica organizează activități de promovare a lecturii și educației pentru toate vârstele.\n\n\n\n\n\n\n",
      "ru": "Родика Мунтяну – библиотекарь филипеньской мэрии Леова. Он управляет коллекциями книг и ресурсами для чтения, облегчая доступ сообщества к информации и культуре. Родика организует мероприятия по популяризации чтения и образования для людей всех возрастов.",
      "en": "Rodica Munteanu is a librarian at the Filipeni City Hall, Leova. It manages book collections and reading resources, facilitating community access to information and culture. Rodica organizes activities to promote reading and education for all ages.",
      "uk": "",
      "bg": "",
      "tr": "",
      "gag": "",
      "fr": "",
      "de": "",
      "it": "",
      "es": "",
      "pt": "",
      "pl": "",
      "cs": "",
      "sk": "",
      "hu": "",
      "sr": "",
      "hr": "",
      "bs": "",
      "sl": "",
      "mk": "",
      "sq": "",
      "el": "",
      "nl": "",
      "da": "",
      "sv": "",
      "no": "",
      "fi": "",
      "et": "",
      "lv": "",
      "lt": "",
      "is": "",
      "mt": "",
      "ga": ""
    },
    "email": "culturafilipeni@gmail.com",
    "slug": "rodica-munteanu",
    "sections": [
      {
        "type": "TITLE",
        "content": {
          "ro": "Rodica Munteanu – Bibliotecar Principal și Meșter Popular",
          "ru": "Родика Мунтяну – главный библиотекарь и народный мастер",
          "en": "Rodica Munteanu – Principal Librarian and Folk Craftsman",
          "uk": "",
          "bg": "",
          "tr": "",
          "gag": "",
          "fr": "",
          "de": "",
          "it": "",
          "es": "",
          "pt": "",
          "pl": "",
          "cs": "",
          "sk": "",
          "hu": "",
          "sr": "",
          "hr": "",
          "bs": "",
          "sl": "",
          "mk": "",
          "sq": "",
          "el": "",
          "nl": "",
          "da": "",
          "sv": "",
          "no": "",
          "fi": "",
          "et": "",
          "lv": "",
          "lt": "",
          "is": "",
          "mt": "",
          "ga": ""
        }
      },
      {
        "type": "PARAGRAPH",
        "content": {
          "ro": "Rodica Munteanu este o figură dedicată în comunitatea Filipeni, cu o experiență profesională vastă în educație, cultură și activități de meșteșugărit. Activând în diverse funcții de-a lungul carierei sale, Rodica a contribuit la modernizarea bibliotecii locale și la dezvoltarea creativității copiilor din localitate.\n\n",
          "ru": "Родика Мунтяну – преданная фигура в филиппинском сообществе, имеющая обширный профессиональный опыт в сфере образования, культуры и ремесленной деятельности. Занимая различные должности на протяжении всей своей карьеры, Родика внесла свой вклад в модернизацию местной библиотеки и развитие творчества местных детей.",
          "en": "Rodica Munteanu is a dedicated figure in the Filipino community, with extensive professional experience in education, culture and craft activities. Acting in various positions throughout her career, Rodica contributed to the modernization of the local library and to the development of the creativity of local children.",
          "uk": "",
          "bg": "",
          "tr": "",
          "gag": "",
          "fr": "",
          "de": "",
          "it": "",
          "es": "",
          "pt": "",
          "pl": "",
          "cs": "",
          "sk": "",
          "hu": "",
          "sr": "",
          "hr": "",
          "bs": "",
          "sl": "",
          "mk": "",
          "sq": "",
          "el": "",
          "nl": "",
          "da": "",
          "sv": "",
          "no": "",
          "fi": "",
          "et": "",
          "lv": "",
          "lt": "",
          "is": "",
          "mt": "",
          "ga": ""
        }
      },
      {
        "type": "LIST",
        "content": [
          {
            "ro": "Data nașterii: 08.02.1970",
            "ru": "Дата рождения: 08.02.1970 г.",
            "en": "Date of birth: 08.02.1970",
            "uk": "",
            "bg": "",
            "tr": "",
            "gag": "",
            "fr": "",
            "de": "",
            "it": "",
            "es": "",
            "pt": "",
            "pl": "",
            "cs": "",
            "sk": "",
            "hu": "",
            "sr": "",
            "hr": "",
            "bs": "",
            "sl": "",
            "mk": "",
            "sq": "",
            "el": "",
            "nl": "",
            "da": "",
            "sv": "",
            "no": "",
            "fi": "",
            "et": "",
            "lv": "",
            "lt": "",
            "is": "",
            "mt": "",
            "ga": ""
          },
          {
            "ro": "Locul nașterii: satul Sarata-Nouă, raionul Leova, Republica Moldova",
            "ru": "Место рождения: село Сарата Ноуа, Леовский район, Республика Молдова",
            "en": "Place of birth: Sarata Noua village, Leova district, Republic of Moldova",
            "uk": "",
            "bg": "",
            "tr": "",
            "gag": "",
            "fr": "",
            "de": "",
            "it": "",
            "es": "",
            "pt": "",
            "pl": "",
            "cs": "",
            "sk": "",
            "hu": "",
            "sr": "",
            "hr": "",
            "bs": "",
            "sl": "",
            "mk": "",
            "sq": "",
            "el": "",
            "nl": "",
            "da": "",
            "sv": "",
            "no": "",
            "fi": "",
            "et": "",
            "lv": "",
            "lt": "",
            "is": "",
            "mt": "",
            "ga": ""
          }
        ]
      },
      {
        "type": "TITLE",
        "content": {
          "ro": "Parcurs profesional",
          "ru": "Профессиональный путь",
          "en": "Professional path",
          "uk": "",
          "bg": "",
          "tr": "",
          "gag": "",
          "fr": "",
          "de": "",
          "it": "",
          "es": "",
          "pt": "",
          "pl": "",
          "cs": "",
          "sk": "",
          "hu": "",
          "sr": "",
          "hr": "",
          "bs": "",
          "sl": "",
          "mk": "",
          "sq": "",
          "el": "",
          "nl": "",
          "da": "",
          "sv": "",
          "no": "",
          "fi": "",
          "et": "",
          "lv": "",
          "lt": "",
          "is": "",
          "mt": "",
          "ga": ""
        }
      },
      {
        "type": "PARAGRAPH",
        "content": {
          "ro": "Rodica Munteanu și-a început cariera în domeniul educației ca educator la grădinița din Romanovca (1987-2000) și apoi la grădinița din Filipeni (2004-2009). Din 2009, a ocupat postul de dactilograf la primăria Filipeni, iar din același an a devenit bibliotecar principal la Biblioteca pentru Copii Filipeni.\n\n",
          "ru": "Родика Мунтяну начала свою карьеру в сфере образования в качестве воспитателя в детском саду в Романовке (1987-2000), а затем в детском саду в Филиппинах (2004-2009). С 2009 года работал машинисткой в ​​мэрии Филиппин, с того же года стал главным библиотекарем Детской библиотеки Филиппин.",
          "en": "Rodica Munteanu started her career in the field of education as an educator at the kindergarten in Romanovca (1987-2000) and then at the kindergarten in Filipeni (2004-2009). From 2009, he worked as a typist at the Filipeni city hall, and from the same year he became the main librarian at the Filipeni Children's Library.",
          "uk": "",
          "bg": "",
          "tr": "",
          "gag": "",
          "fr": "",
          "de": "",
          "it": "",
          "es": "",
          "pt": "",
          "pl": "",
          "cs": "",
          "sk": "",
          "hu": "",
          "sr": "",
          "hr": "",
          "bs": "",
          "sl": "",
          "mk": "",
          "sq": "",
          "el": "",
          "nl": "",
          "da": "",
          "sv": "",
          "no": "",
          "fi": "",
          "et": "",
          "lv": "",
          "lt": "",
          "is": "",
          "mt": "",
          "ga": ""
        }
      },
      {
        "type": "PARAGRAPH",
        "content": {
          "ro": "În 2010, Rodica a fondat Centrul de creație și creativitate „Lăstărel”, pe care îl conduce cu succes de peste un deceniu, oferind copiilor posibilitatea de a explora meșteșugurile tradiționale și de a dezvolta abilități artistice. În 2012, a primit titlul onorific de „Meșter popular” din partea Ministerului Culturii, ca recunoaștere a contribuțiilor sale în domeniul artizanatului.\n",
          "ru": "В 2010 году Родика основала Центр творчества и творчества «Лэстэрел», которым она успешно руководит уже более десяти лет, предлагая детям возможность изучить традиционные ремесла и развить художественные навыки. В 2012 году он получил почетное звание «Народный мастер» Министерства культуры за заслуги в области ремесел.",
          "en": "In 2010, Rodica founded the \"Lăstărel\" Creation and Creativity Center, which she has been running successfully for over a decade, offering children the opportunity to explore traditional crafts and develop artistic skills. In 2012, he received the honorary title of \"People's Craftsman\" from the Ministry of Culture, in recognition of his contributions in the field of handicrafts.",
          "uk": "",
          "bg": "",
          "tr": "",
          "gag": "",
          "fr": "",
          "de": "",
          "it": "",
          "es": "",
          "pt": "",
          "pl": "",
          "cs": "",
          "sk": "",
          "hu": "",
          "sr": "",
          "hr": "",
          "bs": "",
          "sl": "",
          "mk": "",
          "sq": "",
          "el": "",
          "nl": "",
          "da": "",
          "sv": "",
          "no": "",
          "fi": "",
          "et": "",
          "lv": "",
          "lt": "",
          "is": "",
          "mt": "",
          "ga": ""
        }
      },
      {
        "type": "TITLE",
        "content": {
          "ro": "„Transformarea bibliotecii și serviciile noi”",
          "ru": "«Преобразование библиотеки и новые услуги»",
          "en": "\"Library transformation and new services\"",
          "uk": "",
          "bg": "",
          "tr": "",
          "gag": "",
          "fr": "",
          "de": "",
          "it": "",
          "es": "",
          "pt": "",
          "pl": "",
          "cs": "",
          "sk": "",
          "hu": "",
          "sr": "",
          "hr": "",
          "bs": "",
          "sl": "",
          "mk": "",
          "sq": "",
          "el": "",
          "nl": "",
          "da": "",
          "sv": "",
          "no": "",
          "fi": "",
          "et": "",
          "lv": "",
          "lt": "",
          "is": "",
          "mt": "",
          "ga": ""
        }
      },
      {
        "type": "PARAGRAPH",
        "content": {
          "ro": "Pe parcursul activității sale, Rodica a implementat numeroase servicii moderne de bibliotecă și a colaborat activ cu instituțiile locale. „Mă strădui să transform biblioteca pentru copii într-o bibliotecă modernă, căutată și îndrăgită de utilizatori, unde aceștia să-și poată împlini dorințele spirituale de lectură și frumos.” Ea a lansat inițiative precum „Ora de lectură” și „Pregătirea temei pentru acasă”, organizate în colaborare cu gimnaziul și grădinițele „Andrieș” și „Fluturaș”.\n\n",
          "ru": "За свою карьеру Родика внедрила множество современных библиотечных услуг и активно сотрудничала с местными учреждениями. «Я стремлюсь превратить детскую библиотеку в современную библиотеку, востребованную и любимую пользователями, где они смогут реализовать свои духовные желания чтения и красоты». Она запустила такие инициативы, как «Время чтения» и «Подготовка домашних заданий», организованные в сотрудничестве с гимназией и детскими садами «Андриеш» и «Флутураш».",
          "en": "During her career, Rodica implemented many modern library services and actively collaborated with local institutions. \"I strive to transform the children's library into a modern library, sought after and loved by users, where they can fulfill their spiritual desires of reading and beauty.\" She launched initiatives such as \"Reading time\" and \"Homework preparation\", organized in collaboration with the gymnasium and kindergartens \"Andrieș\" and \"Fluturaș\".",
          "uk": "",
          "bg": "",
          "tr": "",
          "gag": "",
          "fr": "",
          "de": "",
          "it": "",
          "es": "",
          "pt": "",
          "pl": "",
          "cs": "",
          "sk": "",
          "hu": "",
          "sr": "",
          "hr": "",
          "bs": "",
          "sl": "",
          "mk": "",
          "sq": "",
          "el": "",
          "nl": "",
          "da": "",
          "sv": "",
          "no": "",
          "fi": "",
          "et": "",
          "lv": "",
          "lt": "",
          "is": "",
          "mt": "",
          "ga": ""
        }
      },
      {
        "type": "PARAGRAPH",
        "content": {
          "ro": "„Scopul acestor activități este de a deschide o posibilitate de comunicare, o încercare de a repune în drepturi „cartea” și „biblioteca”.” Rodica urmărește să stimuleze interesul copiilor și părinților pentru lectură, văzând aceasta ca pe o plăcere, o relaxare și o sursă de cunoaștere.\n\n",
          "ru": "«Цель этой деятельности — открыть возможность общения, попытаться восстановить права «книги» и «библиотеки». Родика стремится стимулировать интерес детей и родителей к чтению, рассматривая его как удовольствие, отдых и источник знаний.",
          "en": "\"The purpose of these activities is to open a possibility of communication, an attempt to restore the rights of the 'book' and the 'library'.\" Rodica aims to stimulate the interest of children and parents in reading, seeing it as a pleasure, a relaxation and a source of knowledge.",
          "uk": "",
          "bg": "",
          "tr": "",
          "gag": "",
          "fr": "",
          "de": "",
          "it": "",
          "es": "",
          "pt": "",
          "pl": "",
          "cs": "",
          "sk": "",
          "hu": "",
          "sr": "",
          "hr": "",
          "bs": "",
          "sl": "",
          "mk": "",
          "sq": "",
          "el": "",
          "nl": "",
          "da": "",
          "sv": "",
          "no": "",
          "fi": "",
          "et": "",
          "lv": "",
          "lt": "",
          "is": "",
          "mt": "",
          "ga": ""
        }
      },
      {
        "type": "TITLE",
        "content": {
          "ro": "Centrul de creație și creativitate „Lăstărel”",
          "ru": "Центр творчества и творчества «Лэстарель»",
          "en": "Creation and creativity center \"Lăstarel\"",
          "uk": "",
          "bg": "",
          "tr": "",
          "gag": "",
          "fr": "",
          "de": "",
          "it": "",
          "es": "",
          "pt": "",
          "pl": "",
          "cs": "",
          "sk": "",
          "hu": "",
          "sr": "",
          "hr": "",
          "bs": "",
          "sl": "",
          "mk": "",
          "sq": "",
          "el": "",
          "nl": "",
          "da": "",
          "sv": "",
          "no": "",
          "fi": "",
          "et": "",
          "lv": "",
          "lt": "",
          "is": "",
          "mt": "",
          "ga": ""
        }
      },
      {
        "type": "PARAGRAPH",
        "content": {
          "ro": "Fondat în 2009, centrul este dedicat dezvoltării abilităților artistice ale copiilor din comunitate. Rodica colaborează cu tineri cu vârste între 9 și 16 ani, organizând ateliere de meșteșugărit care includ lucrul cu pănușa de porumb, croșetare, origami și ornamente din materiale naturale.",
          "ru": "Центр, основанный в 2009 году, занимается развитием художественных навыков детей в обществе. Родика сотрудничает с молодежью от 9 до 16 лет, организуя мастер-классы по рукоделию, включающие работу с початками кукурузы, вязание крючком, оригами и украшениями из природных материалов.",
          "en": "Founded in 2009, the center is dedicated to developing the artistic skills of children in the community. Rodica collaborates with young people between the ages of 9 and 16, organizing craft workshops that include working with corn cob, crochet, origami and ornaments from natural materials.",
          "uk": "",
          "bg": "",
          "tr": "",
          "gag": "",
          "fr": "",
          "de": "",
          "it": "",
          "es": "",
          "pt": "",
          "pl": "",
          "cs": "",
          "sk": "",
          "hu": "",
          "sr": "",
          "hr": "",
          "bs": "",
          "sl": "",
          "mk": "",
          "sq": "",
          "el": "",
          "nl": "",
          "da": "",
          "sv": "",
          "no": "",
          "fi": "",
          "et": "",
          "lv": "",
          "lt": "",
          "is": "",
          "mt": "",
          "ga": ""
        }
      },
      {
        "type": "GALLERY",
        "slidesPerView": 2,
        "content": [
          "67200b06ee25fe40ed70ff6c",
          "67200b07ee25fe40ed70ff74",
          "67200b05ee25fe40ed70ff5f"
        ]
      },
      {
        "type": "GALLERY",
        "slidesPerView": 2,
        "content": [
          "670f7fcae82843ce53a60935",
          "670f7fd1e82843ce53a60936",
          "670f7fd5e82843ce53a60937",
          "670f7fc5e82843ce53a60934"
        ]
      },
      {
        "type": "PARAGRAPH",
        "content": {
          "ro": "„Mă strădui mereu să fiu disponibilă la solicitările copiilor de diferite vârste și copiilor cu dizabilități, pentru a perfecționa activitățile practice și fantezia.” Lucrările create de copii au fost expuse la expoziții raionale și naționale, primind aprecieri pentru valoarea lor artistică.\n\n",
          "ru": "«Я всегда стараюсь быть доступной к запросам детей разного возраста и детей с ограниченными возможностями, развивать практическую деятельность и фантазию». Работы, созданные детьми, экспонировались на районных и республиканских выставках, получая высокую оценку своей художественной ценности.",
          "en": "\"I always try to be available to the requests of children of different ages and children with disabilities, to improve practical activities and fantasy.\" The works created by the children have been exhibited at district and national exhibitions, receiving appreciation for their artistic value.",
          "uk": "",
          "bg": "",
          "tr": "",
          "gag": "",
          "fr": "",
          "de": "",
          "it": "",
          "es": "",
          "pt": "",
          "pl": "",
          "cs": "",
          "sk": "",
          "hu": "",
          "sr": "",
          "hr": "",
          "bs": "",
          "sl": "",
          "mk": "",
          "sq": "",
          "el": "",
          "nl": "",
          "da": "",
          "sv": "",
          "no": "",
          "fi": "",
          "et": "",
          "lv": "",
          "lt": "",
          "is": "",
          "mt": "",
          "ga": ""
        }
      },
      {
        "type": "EMPHASIZED_PARAGRAPH",
        "content": {
          "ro": "Cuvântul de ordine al centrului este: „Viitorul aparține celor ce cred în frumusețea propriilor vise.”\n\n",
          "ru": "Девиз центра: «Будущее принадлежит тем, кто верит в красоту своей мечты».",
          "en": "The motto of the center is: \"The future belongs to those who believe in the beauty of their own dreams.\"",
          "uk": "",
          "bg": "",
          "tr": "",
          "gag": "",
          "fr": "",
          "de": "",
          "it": "",
          "es": "",
          "pt": "",
          "pl": "",
          "cs": "",
          "sk": "",
          "hu": "",
          "sr": "",
          "hr": "",
          "bs": "",
          "sl": "",
          "mk": "",
          "sq": "",
          "el": "",
          "nl": "",
          "da": "",
          "sv": "",
          "no": "",
          "fi": "",
          "et": "",
          "lv": "",
          "lt": "",
          "is": "",
          "mt": "",
          "ga": ""
        }
      },
      {
        "type": "TITLE",
        "content": {
          "ro": "Îmbunătățirea continuă a competențelor profesionale",
          "ru": "Постоянное повышение профессиональных навыков",
          "en": "Continuous improvement of professional skills",
          "uk": "",
          "bg": "",
          "tr": "",
          "gag": "",
          "fr": "",
          "de": "",
          "it": "",
          "es": "",
          "pt": "",
          "pl": "",
          "cs": "",
          "sk": "",
          "hu": "",
          "sr": "",
          "hr": "",
          "bs": "",
          "sl": "",
          "mk": "",
          "sq": "",
          "el": "",
          "nl": "",
          "da": "",
          "sv": "",
          "no": "",
          "fi": "",
          "et": "",
          "lv": "",
          "lt": "",
          "is": "",
          "mt": "",
          "ga": ""
        }
      },
      {
        "type": "PARAGRAPH",
        "content": {
          "ro": "Rodica participă regulat la cursuri de perfecționare, seminare și traininguri, dezvoltând abilități în domenii precum utilizarea tehnologiei, comunicare și servicii bibliotecare moderne. Ea consideră că un bibliotecar modern trebuie să fie în continuă formare, capabil să răspundă cerințelor unui public din ce în ce mai divers.\n\n",
          "ru": "Родика регулярно участвует в курсах повышения квалификации, семинарах и тренингах, развивая навыки в таких областях, как использование технологий, коммуникации и современные библиотечные услуги. Она считает, что современный библиотекарь должен постоянно проходить обучение, чтобы быть способным удовлетворить запросы все более разнообразной публики.",
          "en": "Rodica regularly participates in refresher courses, seminars and trainings, developing skills in areas such as the use of technology, communication and modern library services. She believes that a modern librarian must be in continuous training, able to meet the demands of an increasingly diverse public.",
          "uk": "",
          "bg": "",
          "tr": "",
          "gag": "",
          "fr": "",
          "de": "",
          "it": "",
          "es": "",
          "pt": "",
          "pl": "",
          "cs": "",
          "sk": "",
          "hu": "",
          "sr": "",
          "hr": "",
          "bs": "",
          "sl": "",
          "mk": "",
          "sq": "",
          "el": "",
          "nl": "",
          "da": "",
          "sv": "",
          "no": "",
          "fi": "",
          "et": "",
          "lv": "",
          "lt": "",
          "is": "",
          "mt": "",
          "ga": ""
        }
      },
      {
        "type": "TITLE",
        "content": {
          "ro": "Direcții de perspectivă",
          "ru": "Перспективные направления",
          "en": "Perspective directions",
          "uk": "",
          "bg": "",
          "tr": "",
          "gag": "",
          "fr": "",
          "de": "",
          "it": "",
          "es": "",
          "pt": "",
          "pl": "",
          "cs": "",
          "sk": "",
          "hu": "",
          "sr": "",
          "hr": "",
          "bs": "",
          "sl": "",
          "mk": "",
          "sq": "",
          "el": "",
          "nl": "",
          "da": "",
          "sv": "",
          "no": "",
          "fi": "",
          "et": "",
          "lv": "",
          "lt": "",
          "is": "",
          "mt": "",
          "ga": ""
        }
      },
      {
        "type": "PARAGRAPH",
        "content": {
          "ro": "Pentru viitor, Rodica Munteanu își propune să:\n\n",
          "ru": "В будущем Родика Мунтяну стремится:",
          "en": "For the future, Rodica Munteanu aims to:",
          "uk": "",
          "bg": "",
          "tr": "",
          "gag": "",
          "fr": "",
          "de": "",
          "it": "",
          "es": "",
          "pt": "",
          "pl": "",
          "cs": "",
          "sk": "",
          "hu": "",
          "sr": "",
          "hr": "",
          "bs": "",
          "sl": "",
          "mk": "",
          "sq": "",
          "el": "",
          "nl": "",
          "da": "",
          "sv": "",
          "no": "",
          "fi": "",
          "et": "",
          "lv": "",
          "lt": "",
          "is": "",
          "mt": "",
          "ga": ""
        }
      },
      {
        "type": "LIST",
        "content": [
          {
            "ro": "Participe la toate seminarele și cursurile disponibile pentru dezvoltarea abilităților moderne de bibliotecar.",
            "ru": "Посещайте все доступные семинары и курсы для развития современных навыков библиотекаря.",
            "en": "Attend all available seminars and courses to develop modern librarian skills.",
            "uk": "",
            "bg": "",
            "tr": "",
            "gag": "",
            "fr": "",
            "de": "",
            "it": "",
            "es": "",
            "pt": "",
            "pl": "",
            "cs": "",
            "sk": "",
            "hu": "",
            "sr": "",
            "hr": "",
            "bs": "",
            "sl": "",
            "mk": "",
            "sq": "",
            "el": "",
            "nl": "",
            "da": "",
            "sv": "",
            "no": "",
            "fi": "",
            "et": "",
            "lv": "",
            "lt": "",
            "is": "",
            "mt": "",
            "ga": ""
          },
          {
            "ro": "Îmbunătățească gestionarea informației și să răspundă prompt la cerințele utilizatorilor.",
            "ru": "Улучшите управление информацией и оперативно реагируйте на требования пользователей.",
            "en": "Improve information management and respond promptly to user requirements.",
            "uk": "",
            "bg": "",
            "tr": "",
            "gag": "",
            "fr": "",
            "de": "",
            "it": "",
            "es": "",
            "pt": "",
            "pl": "",
            "cs": "",
            "sk": "",
            "hu": "",
            "sr": "",
            "hr": "",
            "bs": "",
            "sl": "",
            "mk": "",
            "sq": "",
            "el": "",
            "nl": "",
            "da": "",
            "sv": "",
            "no": "",
            "fi": "",
            "et": "",
            "lv": "",
            "lt": "",
            "is": "",
            "mt": "",
            "ga": ""
          },
          {
            "ro": "Dezvolte condiții mai atractive și interactive în bibliotecă, satisfăcând nevoile utilizatorilor.",
            "ru": "Разработать более привлекательные и интерактивные условия в библиотеке, удовлетворяющие потребности пользователей.",
            "en": "To develop more attractive and interactive conditions in the library, satisfying the needs of users.",
            "uk": "",
            "bg": "",
            "tr": "",
            "gag": "",
            "fr": "",
            "de": "",
            "it": "",
            "es": "",
            "pt": "",
            "pl": "",
            "cs": "",
            "sk": "",
            "hu": "",
            "sr": "",
            "hr": "",
            "bs": "",
            "sl": "",
            "mk": "",
            "sq": "",
            "el": "",
            "nl": "",
            "da": "",
            "sv": "",
            "no": "",
            "fi": "",
            "et": "",
            "lv": "",
            "lt": "",
            "is": "",
            "mt": "",
            "ga": ""
          }
        ]
      }
    ],
    "experience": "14",
    "jobTitle": {
      "ro": "Bibliotecară\t",
      "ru": "Библиотекарь",
      "en": "Librarian",
      "uk": "",
      "bg": "",
      "tr": "",
      "gag": "",
      "fr": "",
      "de": "",
      "it": "",
      "es": "",
      "pt": "",
      "pl": "",
      "cs": "",
      "sk": "",
      "hu": "",
      "sr": "",
      "hr": "",
      "bs": "",
      "sl": "",
      "mk": "",
      "sq": "",
      "el": "",
      "nl": "",
      "da": "",
      "sv": "",
      "no": "",
      "fi": "",
      "et": "",
      "lv": "",
      "lt": "",
      "is": "",
      "mt": "",
      "ga": ""
    },
    "phone": "68491866",
    "skills": [],
    "schools": [
      {
        "from": 1987,
        "to": 2000,
        "title": "Educator la grădinița din Romanovca"
      },
      {
        "from": 2004,
        "to": 2009,
        "title": "Educator la grădinița din Filipeni"
      },
      {
        "from": 2009,
        "to": 2024,
        "title": "Bibliotecar principal la Biblioteca Teritorială pentru Copii din Filipeni"
      },
      {
        "from": 2009,
        "to": 2024,
        "title": "Dactilograf și funcționar la primăria din Filipeni."
      }
    ],
    "order": 6
  }
]
