[
  {
    "_id": {
      "$oid": "6705c8de8221e9146ea19c62"
    },
    "tennant": "moldova",
    "title": {
      "ro": "Cetatea Soroca",
      "ru": "Сорокская крепость",
      "en": "Soroca Fortress"
    },
    "cover": "6721ffc9870b84dbb34681ce",
    "location": {
      "ro": "Moldova",
      "ru": "Молдова",
      "en": "Moldova"
    },
    "date": "2024-10-08T18:04:21.724Z",
    "excerpt": {
      "ro": "O cetate istorică impresionantă de pe malul Nistrului.",
      "ru": "Впечатляющая историческая крепость на берегу Днестра.",
      "en": "An impressive historical fortress on the banks of the Dniester."
    },
    "slug": "cetatea-soroca",
    "sections": [
      {
        "type": "PARAGRAPH",
        "content": {
          "ro": "Cetatea Soroca este o fortăreață moldovenească din secolul al XV-lea, construită de Ion Popescu. Este un monument de arhitectură defensivă și atrage mii de vizitatori anual datorită turnurilor sale rotunde și zidurilor masive.",
          "ru": "Сорокская крепость — молдавская крепость 15-го века, построенная Стефаном Великим. Это памятник оборонительной архитектуры, который ежегодно привлекает тысячи посетителей благодаря своим круглым башням и массивным стенам.",
          "en": "Soroca Fortress is a 15th-century Moldovan fortress built by Stephen the Great. It is a monument of defensive architecture and attracts thousands of visitors annually due to its round towers and massive walls."
        }
      },
      {
        "type": "GALLERY",
        "slidesPerView": 2,
        "content": [
          "67200b02ee25fe40ed70ff25",
          "67200b02ee25fe40ed70ff22",
          "67200b02ee25fe40ed70ff26",
          "67200b02ee25fe40ed70ff27",
          "67200b02ee25fe40ed70ff23"
        ]
      }
    ],
    "viewsCount": 30,
    "createdAt": "2024-10-09T00:05:50.779Z",
    "updatedAt": "2024-11-03T22:42:56.899Z",
    "comments": [],
    "category": {
      "tennant": "moldova",
      "title": {
        "ro": "Cultură",
        "ru": "Культура",
        "en": "Culture"
      },
      "key": "culture"
    }
  },
  {
    "_id": {
      "$oid": "6705c7aa8221e9146ea19c5f"
    },
    "tennant": "moldova",
    "title": {
      "ro": "Complexul Muzeal Orheiul Vechi",
      "ru": "Музейный комплекс Старый Орхей",
      "en": "Old Orhei Museum Complex"
    },
    "cover": "67200b0bee25fe40ed70ffbe",
    "location": {
      "ro": "Moldova",
      "ru": "Молдова",
      "en": "Moldova"
    },
    "date": "2024-10-08T18:04:21.724Z",
    "excerpt": {
      "ro": "Un complex istoric și arheologic spectaculos sculptat în stâncă.",
      "ru": "Захватывающий исторический и археологический комплекс, высеченный в скале.",
      "en": "A spectacular historical and archaeological complex carved in rock."
    },
    "slug": "orheiul-vechi",
    "sections": [
      {
        "type": "PARAGRAPH",
        "content": {
          "ro": "Orheiul Vechi este faimos pentru mănăstirile sale rupestre și peisajele naturale pitorești create de râul Răut. Reprezintă unul dintre cele mai importante situri culturale și spirituale ale Republicii Moldova.",
          "ru": "Старый Орхей славится своими пещерными монастырями и живописными природными ландшафтами, созданными рекой Реут. Это один из самых важных культурных и духовных объектов Республики Молдова.",
          "en": "Old Orhei is famous for its cave monasteries and picturesque natural landscapes created by the Răut River. It represents one of the most important cultural and spiritual sites of the Republic of Moldova."
        }
      },
      {
        "type": "GALLERY",
        "slidesPerView": 2,
        "content": [
          "67200b0cee25fe40ed70ffc2",
          "67200b0bee25fe40ed70ffc0",
          "67200b0bee25fe40ed70ffbf",
          "67200b0bee25fe40ed70ffc1",
          "67200b0cee25fe40ed70ffc4"
        ]
      }
    ],
    "viewsCount": 76,
    "createdAt": "2024-10-09T00:00:42.216Z",
    "updatedAt": "2024-11-03T22:36:23.505Z",
    "comments": [],
    "category": {
      "tennant": "moldova",
      "title": {
        "ro": "Cultură",
        "ru": "Культура",
        "en": "Culture"
      },
      "key": "culture"
    }
  },
  {
    "_id": {
      "$oid": "67234764870b84dbb34681db"
    },
    "tennant": "moldova",
    "title": {
      "ro": "Mănăstirea Căpriana",
      "ru": "Монастырь Кэприяна",
      "en": "Capriana Monastery"
    },
    "cover": "67200b0cee25fe40ed70ffcc",
    "location": {
      "ro": "Moldova",
      "ru": "Молдова",
      "en": "Moldova"
    },
    "date": "2024-10-30T08:49:40.130Z",
    "excerpt": {
      "ro": "Una dintre cele mai vechi mănăstiri din Republica Moldova.",
      "ru": "Один из старейших монастырей Республики Молдова.",
      "en": "One of the oldest monasteries in the Republic of Moldova."
    },
    "slug": "manastirea-capriana",
    "sections": [
      {
        "type": "PARAGRAPH",
        "content": {
          "ro": "Mănăstirea Căpriana, așezată într-o zonă pitorească de codru, este un lăcaș de cult istoric, fondat în secolul al XV-lea. Aceasta a fost mult timp sediul mitropoliei Moldovei și a fost restaurată recent.",
          "ru": "Монастырь Кэприяна, расположенный в живописной лесной зоне, является историческим местом культа, основанным в 15 веке. Долгое время он был резиденцией митрополии Молдовы и недавно был отреставрирован.",
          "en": "Capriana Monastery, located in a picturesque forest area, is a historical place of worship, founded in the 15th century. It was long the seat of the Moldovan metropolis and was recently restored."
        }
      },
      {
        "type": "GALLERY",
        "slidesPerView": 2,
        "content": [
          "67200b0cee25fe40ed70ffcd",
          "67200b0cee25fe40ed70ffcc",
          "67200b0cee25fe40ed70ffce"
        ]
      }
    ],
    "viewsCount": 32,
    "createdAt": "2024-10-31T09:01:24.734Z",
    "updatedAt": "2024-11-03T22:42:26.027Z",
    "comments": [],
    "category": {
      "tennant": "moldova",
      "title": {
        "ro": "Cultură",
        "ru": "Культура",
        "en": "Culture"
      },
      "key": "culture"
    }
  },
  {
    "_id": {
      "$oid": "67089c92d04e684bae444669"
    },
    "tennant": "moldova",
    "title": {
      "ro": "Arcul de Triumf din Chișinău",
      "ru": "Триумфальная арка Кишинева",
      "en": "Triumphal Arch in Chisinau"
    },
    "cover": "67200b02ee25fe40ed70ff20",
    "location": {
      "ro": "Moldova",
      "ru": "Молдова",
      "en": "Moldova"
    },
    "date": "2024-10-11T03:00:14.484Z",
    "excerpt": {
      "ro": "Monument simbolic situat în centrul capitalei Moldovei.",
      "ru": "Символический памятник, расположенный в центре столицы Молдовы.",
      "en": "Symbolic monument located in the center of Moldova's capital."
    },
    "slug": "arcul-de-triumf",
    "sections": [
      {
        "type": "PARAGRAPH",
        "content": {
          "ro": "Arcul de Triumf este un monument de arhitectură situat pe Bulevardul Ion Popescu din Chișinău. A fost construit în secolul al XIX-lea și este unul dintre cele mai fotografiate obiective din capitală.",
          "ru": "Триумфальная арка — архитектурный памятник, расположенный на бульваре Стефана Великого в Кишиневе. Она была построена в 19 веке и является одной из самых фотографируемых достопримечательностей столицы.",
          "en": "The Triumphal Arch is an architectural monument located on Stephen the Great Boulevard in Chisinau. It was built in the 19th century and is one of the most photographed attractions in the capital."
        }
      },
      {
        "type": "GALLERY",
        "slidesPerView": 2,
        "content": [
          "67200b02ee25fe40ed70ff1e",
          "67200b03ee25fe40ed70ff29",
          "67200b02ee25fe40ed70ff20"
        ]
      }
    ],
    "viewsCount": 30,
    "createdAt": "2024-10-11T03:33:38.815Z",
    "updatedAt": "2024-11-03T22:42:49.623Z",
    "comments": [],
    "category": {
      "tennant": "moldova",
      "title": {
        "ro": "Cultură",
        "ru": "Культура",
        "en": "Culture"
      },
      "key": "culture"
    }
  },
  {
    "_id": {
      "$oid": "6705c9bc8221e9146ea19c67"
    },
    "tennant": "moldova",
    "title": {
      "ro": "Castelul Mimi",
      "ru": "Замок Мими",
      "en": "Mimi Castle"
    },
    "cover": "67200b0cee25fe40ed70ffc8",
    "location": {
      "ro": "Moldova",
      "ru": "Молдова",
      "en": "Moldova"
    },
    "date": "2024-10-08T18:04:21.724Z",
    "excerpt": {
      "ro": "Un castel vinicol istoric de o frumusețe arhitecturală deosebită.",
      "ru": "Исторический винный замок необычайной архитектурной красоты.",
      "en": "A historical wine castle of outstanding architectural beauty."
    },
    "slug": "castelul-mimi",
    "sections": [
      {
        "type": "PARAGRAPH",
        "content": {
          "ro": "Castelul Mimi este unul dintre cele mai importante complexe arhitecturale din lumea vinului, construit la sfârșitul secolului al XIX-lea de Constantin Mimi, ultimul guvernator al Basarabiei. Oferă o experiență turistică și enologică de neuitat.",
          "ru": "Замок Мими — один из важнейших архитектурных комплексов в мире вина, построенный в конце 19 века Константином Мими, последним губернатором Бессарабии. Предлагает незабываемый туристический и энологический опыт.",
          "en": "Mimi Castle is one of the most important architectural complexes in the wine world, built at the end of the 19th century by Constantin Mimi, the last governor of Bessarabia. It offers an unforgettable tourist and oenological experience."
        }
      },
      {
        "type": "GALLERY",
        "slidesPerView": 2,
        "content": [
          "67200b0cee25fe40ed70ffc7",
          "67200b0cee25fe40ed70ffc9",
          "67200b0cee25fe40ed70ffc8"
        ]
      }
    ],
    "viewsCount": 16,
    "createdAt": "2024-10-09T00:09:32.613Z",
    "updatedAt": "2024-11-03T22:39:01.963Z",
    "comments": [],
    "category": {
      "tennant": "moldova",
      "title": {
        "ro": "Cultură",
        "ru": "Культура",
        "en": "Culture"
      },
      "key": "culture"
    }
  }
]